radiflow_folder_upload/__init__.py
radiflow_folder_upload/example.py
radiflow_folder_upload/frontend/build/asset-manifest.json
radiflow_folder_upload/frontend/build/bootstrap.min.css
radiflow_folder_upload/frontend/build/index.html
radiflow_folder_upload/frontend/build/static/css/main.d392e128.css
radiflow_folder_upload/frontend/build/static/css/main.d392e128.css.map
radiflow_folder_upload/frontend/build/static/js/main.03021373.js
radiflow_folder_upload/frontend/build/static/js/main.03021373.js.LICENSE.txt
radiflow_folder_upload/frontend/build/static/js/main.03021373.js.map
radiflow_folder_upload-0.0.1.dist-info/LICENSE
radiflow_folder_upload-0.0.1.dist-info/METADATA
radiflow_folder_upload-0.0.1.dist-info/WHEEL
radiflow_folder_upload-0.0.1.dist-info/top_level.txt
radiflow_folder_upload-0.0.1.dist-info/RECORD
