Metadata-Version: 2.1
Name: radiflow-folder-upload
Version: 0.0.1
Summary: Streamlit component that allows you to do upload folders using a simple websocket connection.
Home-page: UNKNOWN
Author: Sander Hummerich
Author-email: sander.hummerich@med.uni-heidelberg.de
License: UNKNOWN
Platform: UNKNOWN
Requires-Python: >=3.7
License-File: LICENSE
Requires-Dist: streamlit >=0.63
Provides-Extra: devel
Requires-Dist: wheel ; extra == 'devel'
Requires-Dist: pytest ==7.4.0 ; extra == 'devel'
Requires-Dist: playwright ==1.36.0 ; extra == 'devel'
Requires-Dist: requests ==2.31.0 ; extra == 'devel'
Requires-Dist: pytest-playwright-snapshot ==1.0 ; extra == 'devel'
Requires-Dist: pytest-rerunfailures ==12.0 ; extra == 'devel'
